log/__init__.py
log/base_json_log.py
log/base_log.py
log/log_level.py
ildev_log-0.0.3.dist-info/METADATA
ildev_log-0.0.3.dist-info/WHEEL
ildev_log-0.0.3.dist-info/top_level.txt
ildev_log-0.0.3.dist-info/RECORD
